mercupy_msgpack/__init__.py
mercupy_msgpack/_data_elements.py
mercupy_msgpack/_filter_elements.py
mercupy_msgpack/_manifest_elements.py
mercupy_msgpack/_tags.py
mercupy_msgpack-0.0.0.dist-info/METADATA
mercupy_msgpack-0.0.0.dist-info/WHEEL
mercupy_msgpack-0.0.0.dist-info/licenses/LICENSE
mercupy_msgpack-0.0.0.dist-info/RECORD
